mn_slack_logger/__init__.py
mn_slack_logger/slack_log.py
mn_slack_logger-0.0.8.dist-info/METADATA
mn_slack_logger-0.0.8.dist-info/WHEEL
mn_slack_logger-0.0.8.dist-info/licenses/LICENSE
mn_slack_logger-0.0.8.dist-info/RECORD
