Metadata-Version: 2.4
Name: mn_slack_logger
Version: 0.0.8
Summary: A Python package for logging error messages to a Slack channel
Project-URL: Homepage, https://github.com/Medianova-Tech/mn_slack_logger
Project-URL: Issues, https://github.com/Medianova-Tech/mn_slack_logger/issues
Author-email: Medianova Tech <medianovatech@medianova.com>
License-File: LICENSE
Classifier: License :: OSI Approved :: MIT License
Classifier: Operating System :: OS Independent
Classifier: Programming Language :: Python :: 3
Requires-Python: >=3.6
Requires-Dist: requests>=2.25.1
